[
    {
        "name": "Star Sports 1",
        "id": "star1in",
        "logo": "https://raw.githubusercontent.com/abusaeeidx/Tv-Channel-Logo/heads/main/CricHD/runded/16-by-xfireflix.png",
        "link": "https://off1.gogohaalmal.com:1686/hls/star1in.m3u8?md5=dqgWix207VpYa13cQLeL0g&expires=1751323944",
        "referer": "https://stylisheleg4nt.com",
        "origin": "https://stylisheleg4nt.com"
    },
    {
        "name": "Star Sports 1 Hindi",
        "id": "starhindi",
        "logo": "https://raw.githubusercontent.com/abusaeeidx/Tv-Channel-Logo/heads/main/CricHD/runded/1-by-xfireflix.png",
        "link": "https://off1.gogohaalmal.com:1686/hls/starhindi.m3u8?md5=jb7nCwwO1eYv-UFjTBEodA&expires=1751323945",
        "referer": "https://stylisheleg4nt.com",
        "origin": "https://stylisheleg4nt.com"
    },
    {
        "name": "PTV Sports",
        "id": "ptvpk",
        "logo": "https://raw.githubusercontent.com/abusaeeidx/Tv-Channel-Logo/heads/main/CricHD/runded/20-by-xfireflix.png",
        "link": "https://off1.gogohaalmal.com:1686/hls/ptvpk.m3u8?md5=hsXCfIyaxrg58LkXY5m_Aw&expires=1751323945",
        "referer": "https://stylisheleg4nt.com",
        "origin": "https://stylisheleg4nt.com"
    },
    {
        "name": "Willow HD",
        "id": "willowusa",
        "logo": "https://raw.githubusercontent.com/abusaeeidx/Tv-Channel-Logo/heads/main/CricHD/runded/38-by-xfireflix.png",
        "link": "https://off1.gogohaalmal.com:1686/hls/willowusa.m3u8?md5=nAi5FGjP-ITMTWL_8nHy-Q&expires=1751323945",
        "referer": "https://stylisheleg4nt.com",
        "origin": "https://stylisheleg4nt.com"
    },
    {
        "name": "Willow HD 2",
        "id": "willowextra",
        "logo": "https://raw.githubusercontent.com/abusaeeidx/Tv-Channel-Logo/heads/main/CricHD/runded/8-by-xfireflix.png",
        "link": "https://off1.gogohaalmal.com:1686/hls/willowextra.m3u8?md5=-w6zLTEiIqO1fIUR1asAGQ&expires=1751323945",
        "referer": "https://stylisheleg4nt.com",
        "origin": "https://stylisheleg4nt.com"
    },
    {
        "name": "Ten Sports",
        "id": "tenspk",
        "logo": "https://raw.githubusercontent.com/abusaeeidx/Tv-Channel-Logo/heads/main/CricHD/runded/10-by-xfireflix.png",
        "link": "https://off1.gogohaalmal.com:1686/hls/tenspk.m3u8?md5=mR34sMnTDg8tfHpkP30eTw&expires=1751323946",
        "referer": "https://stylisheleg4nt.com",
        "origin": "https://stylisheleg4nt.com"
    },
    {
        "name": "A Sports HD",
        "id": "asportshd",
        "logo": "https://raw.githubusercontent.com/abusaeeidx/Tv-Channel-Logo/heads/main/CricHD/runded/12-by-xfireflix.png",
        "link": "https://off1.gogohaalmal.com:1686/hls/asportshd.m3u8?md5=LJr09abQCF_knbel1MLVrw&expires=1751323946",
        "referer": "https://stylisheleg4nt.com",
        "origin": "https://stylisheleg4nt.com"
    },
    {
        "name": "Sky Sports Cricket",
        "id": "skyscric",
        "logo": "https://raw.githubusercontent.com/abusaeeidx/Tv-Channel-Logo/heads/main/CricHD/runded/9-by-xfireflix.png",
        "link": "https://off1.gogohaalmal.com:1686/hls/skyscric.m3u8?md5=X1N5Y-FVOJ2LX6gB2VS9Zg&expires=1751323946",
        "referer": "https://stylisheleg4nt.com",
        "origin": "https://stylisheleg4nt.com"
    },
    {
        "name": "Sky Sports Main Event",
        "id": "skysme",
        "logo": "https://raw.githubusercontent.com/abusaeeidx/Tv-Channel-Logo/heads/main/CricHD/runded/18-by-xfireflix.png",
        "link": "https://off1.gogohaalmal.com:1686/hls/skysme.m3u8?md5=ydj5wy9UkdkZfIryySWaLQ&expires=1751323946",
        "referer": "https://stylisheleg4nt.com",
        "origin": "https://stylisheleg4nt.com"
    },
    {
        "name": "TNT 1",
        "id": "bbtsp1",
        "logo": "https://raw.githubusercontent.com/abusaeeidx/Tv-Channel-Logo/heads/main/CricHD/runded/tnt.png",
        "link": "https://off1.gogohaalmal.com:1686/hls/bbtsp1.m3u8?md5=0Kg6HkENrTRE-cPok5S1GQ&expires=1751323947",
        "referer": "https://stylisheleg4nt.com",
        "origin": "https://stylisheleg4nt.com"
    },
    {
        "name": "TNT 2",
        "id": "bbtsp2",
        "logo": "https://raw.githubusercontent.com/abusaeeidx/Tv-Channel-Logo/heads/main/CricHD/runded/tnt.png",
        "link": "https://off1.gogohaalmal.com:1686/hls/bbtsp2.m3u8?md5=mCSJZ77yHEHhdpJW5ReJdQ&expires=1751323947",
        "referer": "https://stylisheleg4nt.com",
        "origin": "https://stylisheleg4nt.com"
    },
    {
        "name": "TNT 3",
        "id": "bbtsp3",
        "logo": "https://raw.githubusercontent.com/abusaeeidx/Tv-Channel-Logo/heads/main/CricHD/runded/tnt.png",
        "link": "https://off1.gogohaalmal.com:1686/hls/bbtsp3.m3u8?md5=ess1SLmcEPVJCrhOuJSaAA&expires=1751323947",
        "referer": "https://stylisheleg4nt.com",
        "origin": "https://stylisheleg4nt.com"
    },
    {
        "name": "TNT 4",
        "id": "bbtespn",
        "logo": "https://raw.githubusercontent.com/abusaeeidx/Tv-Channel-Logo/heads/main/CricHD/runded/tnt.png",
        "link": "https://off1.gogohaalmal.com:1686/hls/bbtespn.m3u8?md5=JC_6JijqX1C9JNSnfo9tLA&expires=1751323948",
        "referer": "https://stylisheleg4nt.com",
        "origin": "https://stylisheleg4nt.com"
    },
    {
        "name": "Sky Sports 1",
        "id": "sky1nz",
        "logo": "https://raw.githubusercontent.com/abusaeeidx/Tv-Channel-Logo/heads/main/CricHD/runded/56-by-xfireflix.png",
        "link": "https://off1.gogohaalmal.com:1686/hls/sky1nz.m3u8?md5=YmVFeTz5rQ_Zzjrh7Kbf9w&expires=1751323948",
        "referer": "https://stylisheleg4nt.com",
        "origin": "https://stylisheleg4nt.com"
    },
    {
        "name": "Sky Sports 2",
        "id": "sky2nz",
        "logo": "https://raw.githubusercontent.com/abusaeeidx/Tv-Channel-Logo/heads/main/CricHD/runded/56-by-xfireflix.png",
        "link": "https://off1.gogohaalmal.com:1686/hls/sky2nz.m3u8?md5=Qm9bbabBYn2laLL1l8JINg&expires=1751323948",
        "referer": "https://stylisheleg4nt.com",
        "origin": "https://stylisheleg4nt.com"
    },
    {
        "name": "Sky Sports 3",
        "id": "sky3nz",
        "logo": "https://raw.githubusercontent.com/abusaeeidx/Tv-Channel-Logo/heads/main/CricHD/runded/56-by-xfireflix.png",
        "link": "https://off1.gogohaalmal.com:1686/hls/sky3nz.m3u8?md5=bNt7RUEeI5d5xXQsCKtgFw&expires=1751323948",
        "referer": "https://stylisheleg4nt.com",
        "origin": "https://stylisheleg4nt.com"
    },
    {
        "name": "Sky Sports 4",
        "id": "sky4nz",
        "logo": "https://raw.githubusercontent.com/abusaeeidx/Tv-Channel-Logo/heads/main/CricHD/runded/56-by-xfireflix.png",
        "link": "https://off1.gogohaalmal.com:1686/hls/sky4nz.m3u8?md5=ql98yWu0Eu8hSj3xWf5lHQ&expires=1751323949",
        "referer": "https://stylisheleg4nt.com",
        "origin": "https://stylisheleg4nt.com"
    },
    {
        "name": "Sky Sports 5",
        "id": "sky5nz",
        "logo": "https://raw.githubusercontent.com/abusaeeidx/Tv-Channel-Logo/heads/main/CricHD/runded/56-by-xfireflix.png",
        "link": "https://off1.gogohaalmal.com:1686/hls/sky5nz.m3u8?md5=aBq_mpbnSna-GCMnj2ZmEw&expires=1751323949",
        "referer": "https://stylisheleg4nt.com",
        "origin": "https://stylisheleg4nt.com"
    },
    {
        "name": "Sky Sports 6",
        "id": "sky6nz",
        "logo": "https://raw.githubusercontent.com/abusaeeidx/Tv-Channel-Logo/heads/main/CricHD/runded/56-by-xfireflix.png",
        "link": "https://off1.gogohaalmal.com:1686/hls/sky6nz.m3u8?md5=7IoVtzsAM4c4L6SFh2hkDg&expires=1751323949",
        "referer": "https://stylisheleg4nt.com",
        "origin": "https://stylisheleg4nt.com"
    },
    {
        "name": "Sky Sports 7",
        "id": "sky7nz",
        "logo": "https://raw.githubusercontent.com/abusaeeidx/Tv-Channel-Logo/heads/main/CricHD/runded/56-by-xfireflix.png",
        "link": "https://off1.gogohaalmal.com:1686/hls/sky7nz.m3u8?md5=BK9AZEP3zMUcn2ND5CRz7Q&expires=1751323949",
        "referer": "https://stylisheleg4nt.com",
        "origin": "https://stylisheleg4nt.com"
    },
    {
        "name": "Sky Sports 8",
        "id": "sky8nz",
        "logo": "https://raw.githubusercontent.com/abusaeeidx/Tv-Channel-Logo/heads/main/CricHD/runded/56-by-xfireflix.png",
        "link": "https://off1.gogohaalmal.com:1686/hls/sky8nz.m3u8?md5=3kisapwKRe7ghGoG-_oG0w&expires=1751323950",
        "referer": "https://stylisheleg4nt.com",
        "origin": "https://stylisheleg4nt.com"
    },
    {
        "name": "Sky Sports 9",
        "id": "sky9nz",
        "logo": "https://raw.githubusercontent.com/abusaeeidx/Tv-Channel-Logo/heads/main/CricHD/runded/56-by-xfireflix.png",
        "link": "https://off1.gogohaalmal.com:1686/hls/sky9nz.m3u8?md5=UDWG62ELfzlQpHr2tMLcVQ&expires=1751323950",
        "referer": "https://stylisheleg4nt.com",
        "origin": "https://stylisheleg4nt.com"
    },
    {
        "name": "Sky Cinema",
        "id": "skysme",
        "logo": "https://raw.githubusercontent.com/abusaeeidx/Tv-Channel-Logo/heads/main/CricHD/runded/skycinema.png",
        "link": "https://off1.gogohaalmal.com:1686/hls/skysme.m3u8?md5=HWrdTSpjZxTtustX6K8ftw&expires=1751323950",
        "referer": "https://stylisheleg4nt.com",
        "origin": "https://stylisheleg4nt.com"
    },
    {
        "name": "Sky Sports Action",
        "id": "skysact",
        "logo": "https://raw.githubusercontent.com/abusaeeidx/Tv-Channel-Logo/heads/main/CricHD/runded/1745007829332.png",
        "link": "https://off1.gogohaalmal.com:1686/hls/skysact.m3u8?md5=chtlKFrGc7d02aY-QkvUeg&expires=1751323951",
        "referer": "https://stylisheleg4nt.com",
        "origin": "https://stylisheleg4nt.com"
    },
    {
        "name": "Sky Sports Golf",
        "id": "skysgol",
        "logo": "https://raw.githubusercontent.com/abusaeeidx/Tv-Channel-Logo/heads/main/CricHD/runded/1745008055327.png",
        "link": "https://off1.gogohaalmal.com:1686/hls/skysgol.m3u8?md5=VhGv0AyQzvWAhqEB24oxMw&expires=1751323951",
        "referer": "https://stylisheleg4nt.com",
        "origin": "https://stylisheleg4nt.com"
    },
    {
        "name": "Sky Sports Premier League",
        "id": "skysprem",
        "logo": "https://raw.githubusercontent.com/abusaeeidx/Tv-Channel-Logo/heads/main/CricHD/runded/43-by-xfireflix.png",
        "link": "https://off1.gogohaalmal.com:1686/hls/skysprem.m3u8?md5=svFcFFgV-RFqYd_2Dc0vEw&expires=1751323951",
        "referer": "https://stylisheleg4nt.com",
        "origin": "https://stylisheleg4nt.com"
    },
    {
        "name": "Sky Sports Football",
        "id": "skysfott",
        "logo": "https://raw.githubusercontent.com/abusaeeidx/Tv-Channel-Logo/heads/main/CricHD/runded/44-by-xfireflix.png",
        "link": "https://off1.gogohaalmal.com:1686/hls/skysfott.m3u8?md5=tAsXYgBJawzEFzLM4WJxHA&expires=1751323951",
        "referer": "https://stylisheleg4nt.com",
        "origin": "https://stylisheleg4nt.com"
    },
    {
        "name": "Sky Sports Plus",
        "id": "skysare",
        "logo": "https://raw.githubusercontent.com/abusaeeidx/Tv-Channel-Logo/heads/main/CricHD/runded/1745008347584.png",
        "link": "https://off1.gogohaalmal.com:1686/hls/skysare.m3u8?md5=gh3KbfxShcdVljF2p9_0Ow&expires=1751323951",
        "referer": "https://stylisheleg4nt.com",
        "origin": "https://stylisheleg4nt.com"
    },
    {
        "name": "Sky Sports F1",
        "id": "skysfor1",
        "logo": "https://raw.githubusercontent.com/abusaeeidx/Tv-Channel-Logo/heads/main/CricHD/runded/1745008468637.png",
        "link": "https://off1.gogohaalmal.com:1686/hls/skysfor1.m3u8?md5=Z4xuPVawZObEkZR5Bqu3og&expires=1751323952",
        "referer": "https://stylisheleg4nt.com",
        "origin": "https://stylisheleg4nt.com"
    },
    {
        "name": "LaLiGA",
        "id": "laligauk",
        "logo": "https://raw.githubusercontent.com/abusaeeidx/Tv-Channel-Logo/heads/main/CricHD/runded/19-by-xfireflix.png",
        "link": "https://off1.gogohaalmal.com:1686/hls/laligauk.m3u8?md5=tY3BilO_7zCIGgaXV0vLYw&expires=1751323952",
        "referer": "https://stylisheleg4nt.com",
        "origin": "https://stylisheleg4nt.com"
    },
    {
        "name": "Premier Sports 1",
        "id": "premieruk",
        "logo": "https://raw.githubusercontent.com/abusaeeidx/Tv-Channel-Logo/heads/main/CricHD/runded/31-by-xfireflix.png",
        "link": "https://off1.gogohaalmal.com:1686/hls/premieruk.m3u8?md5=IRoh8M0B79RPoR9Tk4q16A&expires=1751323952",
        "referer": "https://stylisheleg4nt.com",
        "origin": "https://stylisheleg4nt.com"
    },
    {
        "name": "Premier Sports 2",
        "id": "hdchnl2",
        "logo": "https://raw.githubusercontent.com/abusaeeidx/Tv-Channel-Logo/heads/main/CricHD/runded/31-by-xfireflix.png",
        "link": "https://off1.gogohaalmal.com:1686/hls/hdchnl2.m3u8?md5=fuBFL2-7TO3WKpf2ew-OTQ&expires=1751323952",
        "referer": "https://stylisheleg4nt.com",
        "origin": "https://stylisheleg4nt.com"
    },
    {
        "name": "Super Football",
        "id": "superfotball",
        "logo": "https://raw.githubusercontent.com/abusaeeidx/Tv-Channel-Logo/heads/main/CricHD/runded/34-by-xfireflix.png",
        "link": "https://off1.gogohaalmal.com:1686/hls/superfotball.m3u8?md5=lGlD_haJQkIEpo1dVa-okw&expires=1751323953",
        "referer": "https://stylisheleg4nt.com",
        "origin": "https://stylisheleg4nt.com"
    },
    {
        "name": "Super Premier League",
        "id": "superpremier",
        "logo": "https://raw.githubusercontent.com/abusaeeidx/Tv-Channel-Logo/heads/main/CricHD/runded/1745008781606.png",
        "link": "https://off1.gogohaalmal.com:1686/hls/superpremier.m3u8?md5=83N9V1OFm3bnXV6-g-DS6A&expires=1751323953",
        "referer": "https://stylisheleg4nt.com",
        "origin": "https://stylisheleg4nt.com"
    },
    {
        "name": "Astro Cricket",
        "id": "fox501",
        "logo": "https://raw.githubusercontent.com/abusaeeidx/Tv-Channel-Logo/heads/main/CricHD/runded/1745008895589.png",
        "link": "https://off1.gogohaalmal.com:1686/hls/fox501.m3u8?md5=SZ9DQeEnwM2zdzjptVGNzw&expires=1751323953",
        "referer": "https://stylisheleg4nt.com",
        "origin": "https://stylisheleg4nt.com"
    },
    {
        "name": "ESPN 1",
        "id": "espnusa",
        "logo": "https://raw.githubusercontent.com/abusaeeidx/Tv-Channel-Logo/heads/main/CricHD/runded/17-by-xfireflix.png",
        "link": "https://off1.gogohaalmal.com:1686/hls/espnusa.m3u8?md5=pDVegx-cfl1sfVXJU8xHwg&expires=1751323953",
        "referer": "https://stylisheleg4nt.com",
        "origin": "https://stylisheleg4nt.com"
    },
    {
        "name": "ESPN 2",
        "id": "espn2",
        "logo": "https://raw.githubusercontent.com/abusaeeidx/Tv-Channel-Logo/heads/main/CricHD/runded/17-by-xfireflix.png",
        "link": "https://off1.gogohaalmal.com:1686/hls/espn2.m3u8?md5=BmlyIjUW87YkLZZR4SYvMw&expires=1751323954",
        "referer": "https://stylisheleg4nt.com",
        "origin": "https://stylisheleg4nt.com"
    },
    {
        "name": "Sky Sports Arena",
        "id": "skysare",
        "logo": "https://raw.githubusercontent.com/abusaeeidx/Tv-Channel-Logo/heads/main/CricHD/runded/1745007829327.png",
        "link": "https://off1.gogohaalmal.com:1686/hls/skysare.m3u8?md5=COJrgSU1gV3xOFj9uSudrQ&expires=1751323954",
        "referer": "https://stylisheleg4nt.com",
        "origin": "https://stylisheleg4nt.com"
    },
    {
        "name": "Sky Sports Mix",
        "id": "skysmixx",
        "logo": "https://raw.githubusercontent.com/abusaeeidx/Tv-Channel-Logo/heads/main/CricHD/runded/13-by-xfireflix.png",
        "link": "https://off1.gogohaalmal.com:1686/hls/skysmixx.m3u8?md5=6JcmPeL7xOz3MkGUYRjpuQ&expires=1751323954",
        "referer": "https://stylisheleg4nt.com",
        "origin": "https://stylisheleg4nt.com"
    },
    {
        "name": "Sky Sports Tennis",
        "id": "skystennis",
        "logo": "https://raw.githubusercontent.com/abusaeeidx/Tv-Channel-Logo/heads/main/CricHD/runded/1745009085794.png",
        "link": "https://off1.gogohaalmal.com:1686/hls/skystennis.m3u8?md5=CUkD97-WyyFEsI7WSJTvLA&expires=1751323954",
        "referer": "https://stylisheleg4nt.com",
        "origin": "https://stylisheleg4nt.com"
    },
    {
        "name": "Fox Cricket 501 HD",
        "id": "fox501",
        "logo": "https://raw.githubusercontent.com/abusaeeidx/Tv-Channel-Logo/heads/main/CricHD/runded/6-by-xfireflix.png",
        "link": "https://off1.gogohaalmal.com:1686/hls/fox501.m3u8?md5=zlTXESOuagje1FCNQc8M1A&expires=1751323954",
        "referer": "https://stylisheleg4nt.com",
        "origin": "https://stylisheleg4nt.com"
    },
    {
        "name": "Sony Sports3",
        "id": "ten1hd",
        "logo": "https://raw.githubusercontent.com/abusaeeidx/Tv-Channel-Logo/heads/main/CricHD/runded/1000173192-modified.png",
        "link": "https://off1.gogohaalmal.com:1686/hls/ten1hd.m3u8?md5=xy6f_1myBDP8LoBSMXfOVg&expires=1751323955",
        "referer": "https://stylisheleg4nt.com",
        "origin": "https://stylisheleg4nt.com"
    }
]