[
    {
        "name": "Star Sports 1",
        "id": "star1in",
        "logo": "https://cdn.jsdelivr.net/gh/HelloPeopleTv4you/tv-logo@refs/heads/main/crichd2-runded/16-by-xfireflix.png",
        "link": "https://off1.gogohaalmal.com:1686/hls/star1in.m3u8?md5=uSRtZGlm2wLOujNGbb3omQ&expires=1747525784",
        "referer": "https://stylisheleg4nt.com",
        "origin": "https://stylisheleg4nt.com"
    },
    {
        "name": "Star Sports 1 Hindi",
        "id": "starhindi",
        "logo": "https://cdn.jsdelivr.net/gh/HelloPeopleTv4you/tv-logo@refs/heads/main/crichd2-runded/1-by-xfireflix.png",
        "link": "https://m4.merichunidya.com:999/hls/starhindi.m3u8?md5=NiXeTHj7ML26CZq7dFQVug&expires=1747525785",
        "referer": "https://stylisheleg4nt.com",
        "origin": "https://stylisheleg4nt.com"
    },
    {
        "name": "PTV Sports",
        "id": "ptvpk",
        "logo": "https://cdn.jsdelivr.net/gh/HelloPeopleTv4you/tv-logo@refs/heads/main/crichd2-runded/20-by-xfireflix.png",
        "link": "https://m2.merichunidya.com:999/hls/ptvpk.m3u8?md5=hsN2_27SyZNxpe9v4YJwYA&expires=1747525785",
        "referer": "https://stylisheleg4nt.com",
        "origin": "https://stylisheleg4nt.com"
    },
    {
        "name": "Willow HD",
        "id": "willowusa",
        "logo": "https://cdn.jsdelivr.net/gh/HelloPeopleTv4you/tv-logo@refs/heads/main/crichd2-runded/38-by-xfireflix.png",
        "link": "https://m1.merichunidya.com:999/hls/willowusa.m3u8?md5=FERXbecfMPtXd4wi6Q7IYQ&expires=1747525785",
        "referer": "https://stylisheleg4nt.com",
        "origin": "https://stylisheleg4nt.com"
    },
    {
        "name": "Willow HD 2",
        "id": "willowextra",
        "logo": "https://cdn.jsdelivr.net/gh/HelloPeopleTv4you/tv-logo@refs/heads/main/crichd2-runded/8-by-xfireflix.png",
        "link": "https://m2.merichunidya.com:999/hls/willowextra.m3u8?md5=C614ej5ZjxXpZkaOalX3qw&expires=1747525785",
        "referer": "https://stylisheleg4nt.com",
        "origin": "https://stylisheleg4nt.com"
    },
    {
        "name": "Ten Sports",
        "id": "tenspk",
        "logo": "https://cdn.jsdelivr.net/gh/HelloPeopleTv4you/tv-logo@refs/heads/main/crichd2-runded/10-by-xfireflix.png",
        "link": "https://off1.gogohaalmal.com:1686/hls/tenspk.m3u8?md5=NuGt2bCm3HdzmHhR1eYiMg&expires=1747525785",
        "referer": "https://stylisheleg4nt.com",
        "origin": "https://stylisheleg4nt.com"
    },
    {
        "name": "A Sports HD",
        "id": "asportshd",
        "logo": "https://cdn.jsdelivr.net/gh/HelloPeopleTv4you/tv-logo@refs/heads/main/crichd2-runded/12-by-xfireflix.png",
        "link": "https://off1.gogohaalmal.com:1686/hls/asportshd.m3u8?md5=iOB11VeQN--Zy4jb8l872Q&expires=1747525785",
        "referer": "https://stylisheleg4nt.com",
        "origin": "https://stylisheleg4nt.com"
    },
    {
        "name": "Sky Sports Cricket",
        "id": "skyscric",
        "logo": "https://cdn.jsdelivr.net/gh/HelloPeopleTv4you/tv-logo@refs/heads/main/crichd2-runded/9-by-xfireflix.png",
        "link": "https://m4.merichunidya.com:999/hls/skyscric.m3u8?md5=DAcJb1TneQHisx-YY1NIgg&expires=1747525785",
        "referer": "https://stylisheleg4nt.com",
        "origin": "https://stylisheleg4nt.com"
    },
    {
        "name": "Sky Sports Main Event",
        "id": "skysme",
        "logo": "https://cdn.jsdelivr.net/gh/HelloPeopleTv4you/tv-logo@refs/heads/main/crichd2-runded/18-by-xfireflix.png",
        "link": "https://m4.merichunidya.com:999/hls/skysme.m3u8?md5=ThPXlo_jXjvFhVj79B94KQ&expires=1747525785",
        "referer": "https://stylisheleg4nt.com",
        "origin": "https://stylisheleg4nt.com"
    },
    {
        "name": "TNT 1",
        "id": "bbtsp1",
        "logo": "https://cdn.jsdelivr.net/gh/HelloPeopleTv4you/tv-logo@refs/heads/main/crichd2-runded/tnt.png",
        "link": "https://m1.merichunidya.com:999/hls/bbtsp1.m3u8?md5=3n8eUm8AJI42K48TiyfDiQ&expires=1747525785",
        "referer": "https://stylisheleg4nt.com",
        "origin": "https://stylisheleg4nt.com"
    },
    {
        "name": "TNT 2",
        "id": "bbtsp2",
        "logo": "https://cdn.jsdelivr.net/gh/HelloPeopleTv4you/tv-logo@refs/heads/main/crichd2-runded/tnt.png",
        "link": "https://off1.gogohaalmal.com:1686/hls/bbtsp2.m3u8?md5=VuLQS8-MHVNeAEjYidE3Sg&expires=1747525785",
        "referer": "https://stylisheleg4nt.com",
        "origin": "https://stylisheleg4nt.com"
    },
    {
        "name": "TNT 3",
        "id": "bbtsp3",
        "logo": "https://cdn.jsdelivr.net/gh/HelloPeopleTv4you/tv-logo@refs/heads/main/crichd2-runded/tnt.png",
        "link": "https://m1.merichunidya.com:999/hls/bbtsp3.m3u8?md5=bGdd9cH_4ydvGn6IFwpjtw&expires=1747525785",
        "referer": "https://stylisheleg4nt.com",
        "origin": "https://stylisheleg4nt.com"
    },
    {
        "name": "TNT 4",
        "id": "bbtespn",
        "logo": "https://cdn.jsdelivr.net/gh/HelloPeopleTv4you/tv-logo@refs/heads/main/crichd2-runded/tnt.png",
        "link": "https://m1.merichunidya.com:999/hls/bbtespn.m3u8?md5=oqdHoxATe3S4rZShOxzDbg&expires=1747525785",
        "referer": "https://stylisheleg4nt.com",
        "origin": "https://stylisheleg4nt.com"
    },
    {
        "name": "Sky Sports 1",
        "id": "sky1nz",
        "logo": "https://cdn.jsdelivr.net/gh/HelloPeopleTv4you/tv-logo@refs/heads/main/crichd2-runded/56-by-xfireflix.png",
        "link": "https://m4.merichunidya.com:999/hls/sky1nz.m3u8?md5=VuotZJxh6_oN1DOpDa_2ag&expires=1747525785",
        "referer": "https://stylisheleg4nt.com",
        "origin": "https://stylisheleg4nt.com"
    },
    {
        "name": "Sky Sports 2",
        "id": "sky2nz",
        "logo": "https://cdn.jsdelivr.net/gh/HelloPeopleTv4you/tv-logo@refs/heads/main/crichd2-runded/56-by-xfireflix.png",
        "link": "https://m3.merichunidya.com:999/hls/sky2nz.m3u8?md5=uNpD7Tf4I8XSokTtU9FkwQ&expires=1747525786",
        "referer": "https://stylisheleg4nt.com",
        "origin": "https://stylisheleg4nt.com"
    },
    {
        "name": "Sky Sports 3",
        "id": "sky3nz",
        "logo": "https://cdn.jsdelivr.net/gh/HelloPeopleTv4you/tv-logo@refs/heads/main/crichd2-runded/56-by-xfireflix.png",
        "link": "https://m4.merichunidya.com:999/hls/sky3nz.m3u8?md5=3ylPaAoiH5xyWWpbhL6r9A&expires=1747525786",
        "referer": "https://stylisheleg4nt.com",
        "origin": "https://stylisheleg4nt.com"
    },
    {
        "name": "Sky Sports 4",
        "id": "sky4nz",
        "logo": "https://cdn.jsdelivr.net/gh/HelloPeopleTv4you/tv-logo@refs/heads/main/crichd2-runded/56-by-xfireflix.png",
        "link": "https://m3.merichunidya.com:999/hls/sky4nz.m3u8?md5=RbllLPesypybVwLQD69Q_w&expires=1747525786",
        "referer": "https://stylisheleg4nt.com",
        "origin": "https://stylisheleg4nt.com"
    },
    {
        "name": "Sky Sports 5",
        "id": "sky5nz",
        "logo": "https://cdn.jsdelivr.net/gh/HelloPeopleTv4you/tv-logo@refs/heads/main/crichd2-runded/56-by-xfireflix.png",
        "link": "https://off1.gogohaalmal.com:1686/hls/sky5nz.m3u8?md5=0xrMOR2_kwEDN_UhjfIxoA&expires=1747525786",
        "referer": "https://stylisheleg4nt.com",
        "origin": "https://stylisheleg4nt.com"
    },
    {
        "name": "Sky Sports 6",
        "id": "sky6nz",
        "logo": "https://cdn.jsdelivr.net/gh/HelloPeopleTv4you/tv-logo@refs/heads/main/crichd2-runded/56-by-xfireflix.png",
        "link": "https://m2.merichunidya.com:999/hls/sky6nz.m3u8?md5=fWut_tOIe-yj_WJdRaP4nw&expires=1747525786",
        "referer": "https://stylisheleg4nt.com",
        "origin": "https://stylisheleg4nt.com"
    },
    {
        "name": "Sky Sports 7",
        "id": "sky7nz",
        "logo": "https://cdn.jsdelivr.net/gh/HelloPeopleTv4you/tv-logo@refs/heads/main/crichd2-runded/56-by-xfireflix.png",
        "link": "https://m4.merichunidya.com:999/hls/sky7nz.m3u8?md5=Q0dBxJD1mCc0aJ1LioWPSA&expires=1747525786",
        "referer": "https://stylisheleg4nt.com",
        "origin": "https://stylisheleg4nt.com"
    },
    {
        "name": "Sky Sports 8",
        "id": "sky8nz",
        "logo": "https://cdn.jsdelivr.net/gh/HelloPeopleTv4you/tv-logo@refs/heads/main/crichd2-runded/56-by-xfireflix.png",
        "link": "https://off1.gogohaalmal.com:1686/hls/sky8nz.m3u8?md5=mgmoqn8rDnJ-CHpTWFsfXg&expires=1747525786",
        "referer": "https://stylisheleg4nt.com",
        "origin": "https://stylisheleg4nt.com"
    },
    {
        "name": "Sky Sports 9",
        "id": "sky9nz",
        "logo": "https://cdn.jsdelivr.net/gh/HelloPeopleTv4you/tv-logo@refs/heads/main/crichd2-runded/56-by-xfireflix.png",
        "link": "https://m2.merichunidya.com:999/hls/sky9nz.m3u8?md5=9tA2H1FU_uJzh-f4VfFLXQ&expires=1747525786",
        "referer": "https://stylisheleg4nt.com",
        "origin": "https://stylisheleg4nt.com"
    },
    {
        "name": "Sky Cinema",
        "id": "skysme",
        "logo": "https://cdn.jsdelivr.net/gh/HelloPeopleTv4you/tv-logo@refs/heads/main/crichd2-runded/skycinema.png",
        "link": "https://off1.gogohaalmal.com:1686/hls/skysme.m3u8?md5=eDNsmTs8VQWrOGiU6PljKQ&expires=1747525786",
        "referer": "https://stylisheleg4nt.com",
        "origin": "https://stylisheleg4nt.com"
    },
    {
        "name": "Sky Sports Action",
        "id": "skysact",
        "logo": "https://cdn.jsdelivr.net/gh/HelloPeopleTv4you/tv-logo@refs/heads/main/crichd2-runded/1745007829332.png",
        "link": "https://m3.merichunidya.com:999/hls/skysact.m3u8?md5=V7PSIQns_e1Vq7_ty9wzxw&expires=1747525786",
        "referer": "https://stylisheleg4nt.com",
        "origin": "https://stylisheleg4nt.com"
    },
    {
        "name": "Sky Sports Golf",
        "id": "skysgol",
        "logo": "https://cdn.jsdelivr.net/gh/HelloPeopleTv4you/tv-logo@refs/heads/main/crichd2-runded/1745008055327.png",
        "link": "https://m1.merichunidya.com:999/hls/skysgol.m3u8?md5=IDdcV9e8bxoN3_0YjxfYrA&expires=1747525786",
        "referer": "https://stylisheleg4nt.com",
        "origin": "https://stylisheleg4nt.com"
    },
    {
        "name": "Sky Sports Premier League",
        "id": "skysprem",
        "logo": "https://cdn.jsdelivr.net/gh/HelloPeopleTv4you/tv-logo@refs/heads/main/crichd2-runded/43-by-xfireflix.png",
        "link": "https://off1.gogohaalmal.com:1686/hls/skysprem.m3u8?md5=Nbj6AXzN4voHRwe_QrSx0A&expires=1747525786",
        "referer": "https://stylisheleg4nt.com",
        "origin": "https://stylisheleg4nt.com"
    },
    {
        "name": "Sky Sports Football",
        "id": "skysfott",
        "logo": "https://cdn.jsdelivr.net/gh/HelloPeopleTv4you/tv-logo@refs/heads/main/crichd2-runded/44-by-xfireflix.png",
        "link": "https://m4.merichunidya.com:999/hls/skysfott.m3u8?md5=fPvZzu1dabMyauGW4prNCQ&expires=1747525786",
        "referer": "https://stylisheleg4nt.com",
        "origin": "https://stylisheleg4nt.com"
    },
    {
        "name": "Sky Sports Plus",
        "id": "skysare",
        "logo": "https://cdn.jsdelivr.net/gh/HelloPeopleTv4you/tv-logo@refs/heads/main/crichd2-runded/1745008347584.png",
        "link": "https://m4.merichunidya.com:999/hls/skysare.m3u8?md5=lY9yLgvn5VbrX7MHMbIGXA&expires=1747525786",
        "referer": "https://stylisheleg4nt.com",
        "origin": "https://stylisheleg4nt.com"
    },
    {
        "name": "Sky Sports F1",
        "logo": "https://cdn.jsdelivr.net/gh/HelloPeopleTv4you/tv-logo@refs/heads/main/crichd2-runded/1745008468637.png",
        "error": "Token not found or failed to fetch."
    },
    {
        "name": "LaLiGA",
        "id": "laligauk",
        "logo": "https://cdn.jsdelivr.net/gh/HelloPeopleTv4you/tv-logo@refs/heads/main/crichd2-runded/19-by-xfireflix.png",
        "link": "https://m2.merichunidya.com:999/hls/laligauk.m3u8?md5=3PFhr9fC6Wae_st7xPAUKA&expires=1747525787",
        "referer": "https://stylisheleg4nt.com",
        "origin": "https://stylisheleg4nt.com"
    },
    {
        "name": "Premier Sports 1",
        "id": "premieruk",
        "logo": "https://cdn.jsdelivr.net/gh/HelloPeopleTv4you/tv-logo@refs/heads/main/crichd2-runded/31-by-xfireflix.png",
        "link": "https://m3.merichunidya.com:999/hls/premieruk.m3u8?md5=NwbzCTy98yUbfWKgRaH-_w&expires=1747525787",
        "referer": "https://stylisheleg4nt.com",
        "origin": "https://stylisheleg4nt.com"
    },
    {
        "name": "Premier Sports 2",
        "logo": "https://cdn.jsdelivr.net/gh/HelloPeopleTv4you/tv-logo@refs/heads/main/crichd2-runded/31-by-xfireflix.png",
        "error": "Token not found or failed to fetch."
    },
    {
        "name": "Super Football",
        "id": "superfotball",
        "logo": "https://cdn.jsdelivr.net/gh/HelloPeopleTv4you/tv-logo@refs/heads/main/crichd2-runded/34-by-xfireflix.png",
        "link": "https://m1.merichunidya.com:999/hls/superfotball.m3u8?md5=aGTr05x92oTs1_aUXGaO3Q&expires=1747525787",
        "referer": "https://stylisheleg4nt.com",
        "origin": "https://stylisheleg4nt.com"
    },
    {
        "name": "Super Premier League",
        "id": "superpremier",
        "logo": "https://cdn.jsdelivr.net/gh/HelloPeopleTv4you/tv-logo@refs/heads/main/crichd2-runded/1745008781606.png",
        "link": "https://m4.merichunidya.com:999/hls/superpremier.m3u8?md5=4cpvt4zp8b-oaQf2zk1m7Q&expires=1747525787",
        "referer": "https://stylisheleg4nt.com",
        "origin": "https://stylisheleg4nt.com"
    },
    {
        "name": "Astro Cricket",
        "id": "fox501",
        "logo": "https://cdn.jsdelivr.net/gh/HelloPeopleTv4you/tv-logo@refs/heads/main/crichd2-runded/1745008895589.png",
        "link": "https://m3.merichunidya.com:999/hls/fox501.m3u8?md5=UQ_NdOnkfdueqNP7oCn76g&expires=1747525787",
        "referer": "https://stylisheleg4nt.com",
        "origin": "https://stylisheleg4nt.com"
    },
    {
        "name": "ESPN 1",
        "id": "espnusa",
        "logo": "https://cdn.jsdelivr.net/gh/HelloPeopleTv4you/tv-logo@refs/heads/main/crichd2-runded/17-by-xfireflix.png",
        "link": "https://m1.merichunidya.com:999/hls/espnusa.m3u8?md5=x3VV43tOYwtbgbfLTIJUSg&expires=1747525787",
        "referer": "https://stylisheleg4nt.com",
        "origin": "https://stylisheleg4nt.com"
    },
    {
        "name": "ESPN 2",
        "id": "espn2",
        "logo": "https://cdn.jsdelivr.net/gh/HelloPeopleTv4you/tv-logo@refs/heads/main/crichd2-runded/17-by-xfireflix.png",
        "link": "https://off1.gogohaalmal.com:1686/hls/espn2.m3u8?md5=wi9F9w8RldsLyF5IpwMVlQ&expires=1747525787",
        "referer": "https://stylisheleg4nt.com",
        "origin": "https://stylisheleg4nt.com"
    },
    {
        "name": "Sky Sports Arena",
        "id": "skysare",
        "logo": "https://cdn.jsdelivr.net/gh/HelloPeopleTv4you/tv-logo@refs/heads/main/crichd2-runded/1745007829327.png",
        "link": "https://m1.merichunidya.com:999/hls/skysare.m3u8?md5=i8bCqGpVWp2SUrEpRxet6g&expires=1747525787",
        "referer": "https://stylisheleg4nt.com",
        "origin": "https://stylisheleg4nt.com"
    },
    {
        "name": "Sky Sports Mix",
        "id": "skysmixx",
        "logo": "https://cdn.jsdelivr.net/gh/HelloPeopleTv4you/tv-logo@refs/heads/main/crichd2-runded/13-by-xfireflix.png",
        "link": "https://m1.merichunidya.com:999/hls/skysmixx.m3u8?md5=fiY9uN40Q99dld4uo9QWow&expires=1747525787",
        "referer": "https://stylisheleg4nt.com",
        "origin": "https://stylisheleg4nt.com"
    },
    {
        "name": "Sky Sports Tennis",
        "id": "skystennis",
        "logo": "https://cdn.jsdelivr.net/gh/HelloPeopleTv4you/tv-logo@refs/heads/main/crichd2-runded/1745009085794.png",
        "link": "https://m2.merichunidya.com:999/hls/skystennis.m3u8?md5=MCvpkVnkzRdIzRSP1mSjCA&expires=1747525787",
        "referer": "https://stylisheleg4nt.com",
        "origin": "https://stylisheleg4nt.com"
    },
    {
        "name": "Fox Cricket 501 HD",
        "id": "fox501",
        "logo": "https://cdn.jsdelivr.net/gh/HelloPeopleTv4you/tv-logo@refs/heads/main/crichd2-runded/6-by-xfireflix.png",
        "link": "https://off1.gogohaalmal.com:1686/hls/fox501.m3u8?md5=UQ_NdOnkfdueqNP7oCn76g&expires=1747525787",
        "referer": "https://stylisheleg4nt.com",
        "origin": "https://stylisheleg4nt.com"
    }
]