[
    {
        "name": "Star Sports 1",
        "id": "star1in",
        "logo": "https://raw.githubusercontent.com/abusaeeidx/Tv-Channel-Logo/heads/main/CricHD/runded/16-by-xfireflix.png",
        "link": "https://off1.gogohaalmal.com:1686/hls/star1in.m3u8?md5=n5JtGvpJgTckJPCBpQb_mA&expires=1749459195",
        "referer": "https://stylisheleg4nt.com",
        "origin": "https://stylisheleg4nt.com"
    },
    {
        "name": "Star Sports 1 Hindi",
        "id": "starhindi",
        "logo": "https://raw.githubusercontent.com/abusaeeidx/Tv-Channel-Logo/heads/main/CricHD/runded/1-by-xfireflix.png",
        "link": "https://off1.gogohaalmal.com:1686/hls/starhindi.m3u8?md5=U8tTWHyoLCvQfjj4IPZdmg&expires=1749459195",
        "referer": "https://stylisheleg4nt.com",
        "origin": "https://stylisheleg4nt.com"
    },
    {
        "name": "PTV Sports",
        "id": "ptvpk",
        "logo": "https://raw.githubusercontent.com/abusaeeidx/Tv-Channel-Logo/heads/main/CricHD/runded/20-by-xfireflix.png",
        "link": "https://off1.gogohaalmal.com:1686/hls/ptvpk.m3u8?md5=YyamCU4Q55OGfSk4PkoeGw&expires=1749459195",
        "referer": "https://stylisheleg4nt.com",
        "origin": "https://stylisheleg4nt.com"
    },
    {
        "name": "Willow HD",
        "id": "willowusa",
        "logo": "https://raw.githubusercontent.com/abusaeeidx/Tv-Channel-Logo/heads/main/CricHD/runded/38-by-xfireflix.png",
        "link": "https://off1.gogohaalmal.com:1686/hls/willowusa.m3u8?md5=bpPP1aQXpMUAfhFzC0q7JA&expires=1749459195",
        "referer": "https://stylisheleg4nt.com",
        "origin": "https://stylisheleg4nt.com"
    },
    {
        "name": "Willow HD 2",
        "id": "willowextra",
        "logo": "https://raw.githubusercontent.com/abusaeeidx/Tv-Channel-Logo/heads/main/CricHD/runded/8-by-xfireflix.png",
        "link": "https://off1.gogohaalmal.com:1686/hls/willowextra.m3u8?md5=vvwzzNguPkvE7Iyae_6ATA&expires=1749459195",
        "referer": "https://stylisheleg4nt.com",
        "origin": "https://stylisheleg4nt.com"
    },
    {
        "name": "Ten Sports",
        "id": "tenspk",
        "logo": "https://raw.githubusercontent.com/abusaeeidx/Tv-Channel-Logo/heads/main/CricHD/runded/10-by-xfireflix.png",
        "link": "https://off1.gogohaalmal.com:1686/hls/tenspk.m3u8?md5=qZAYNHbYUFx93J83s7G-hQ&expires=1749459196",
        "referer": "https://stylisheleg4nt.com",
        "origin": "https://stylisheleg4nt.com"
    },
    {
        "name": "A Sports HD",
        "id": "asportshd",
        "logo": "https://raw.githubusercontent.com/abusaeeidx/Tv-Channel-Logo/heads/main/CricHD/runded/12-by-xfireflix.png",
        "link": "https://off1.gogohaalmal.com:1686/hls/asportshd.m3u8?md5=h2CLfUyMmVMIXj6bez0Jhw&expires=1749459196",
        "referer": "https://stylisheleg4nt.com",
        "origin": "https://stylisheleg4nt.com"
    },
    {
        "name": "Sky Sports Cricket",
        "id": "skyscric",
        "logo": "https://raw.githubusercontent.com/abusaeeidx/Tv-Channel-Logo/heads/main/CricHD/runded/9-by-xfireflix.png",
        "link": "https://off1.gogohaalmal.com:1686/hls/skyscric.m3u8?md5=bkRivwDUiSljnjrNk3jGZQ&expires=1749459196",
        "referer": "https://stylisheleg4nt.com",
        "origin": "https://stylisheleg4nt.com"
    },
    {
        "name": "Sky Sports Main Event",
        "id": "skysme",
        "logo": "https://raw.githubusercontent.com/abusaeeidx/Tv-Channel-Logo/heads/main/CricHD/runded/18-by-xfireflix.png",
        "link": "https://off1.gogohaalmal.com:1686/hls/skysme.m3u8?md5=n6M20Xv0pIqCu7kBPf7iXQ&expires=1749459196",
        "referer": "https://stylisheleg4nt.com",
        "origin": "https://stylisheleg4nt.com"
    },
    {
        "name": "TNT 1",
        "logo": "https://raw.githubusercontent.com/abusaeeidx/Tv-Channel-Logo/heads/main/CricHD/runded/tnt.png",
        "error": "Token not found or failed to fetch."
    },
    {
        "name": "TNT 2",
        "id": "bbtsp2",
        "logo": "https://raw.githubusercontent.com/abusaeeidx/Tv-Channel-Logo/heads/main/CricHD/runded/tnt.png",
        "link": "https://off1.gogohaalmal.com:1686/hls/bbtsp2.m3u8?md5=Od6fJYnZx01P4KBKYDl17g&expires=1749459196",
        "referer": "https://stylisheleg4nt.com",
        "origin": "https://stylisheleg4nt.com"
    },
    {
        "name": "TNT 3",
        "id": "bbtsp3",
        "logo": "https://raw.githubusercontent.com/abusaeeidx/Tv-Channel-Logo/heads/main/CricHD/runded/tnt.png",
        "link": "https://off1.gogohaalmal.com:1686/hls/bbtsp3.m3u8?md5=J8glL1J0SuIHmOOSQ21UrQ&expires=1749459196",
        "referer": "https://stylisheleg4nt.com",
        "origin": "https://stylisheleg4nt.com"
    },
    {
        "name": "TNT 4",
        "id": "bbtespn",
        "logo": "https://raw.githubusercontent.com/abusaeeidx/Tv-Channel-Logo/heads/main/CricHD/runded/tnt.png",
        "link": "https://off1.gogohaalmal.com:1686/hls/bbtespn.m3u8?md5=gCnXFF9Iav6DCT1PZWZYIA&expires=1749459196",
        "referer": "https://stylisheleg4nt.com",
        "origin": "https://stylisheleg4nt.com"
    },
    {
        "name": "Sky Sports 1",
        "id": "sky1nz",
        "logo": "https://raw.githubusercontent.com/abusaeeidx/Tv-Channel-Logo/heads/main/CricHD/runded/56-by-xfireflix.png",
        "link": "https://off1.gogohaalmal.com:1686/hls/sky1nz.m3u8?md5=eQkPa-Shh40Htlr1OY_QTg&expires=1749459196",
        "referer": "https://stylisheleg4nt.com",
        "origin": "https://stylisheleg4nt.com"
    },
    {
        "name": "Sky Sports 2",
        "id": "sky2nz",
        "logo": "https://raw.githubusercontent.com/abusaeeidx/Tv-Channel-Logo/heads/main/CricHD/runded/56-by-xfireflix.png",
        "link": "https://off1.gogohaalmal.com:1686/hls/sky2nz.m3u8?md5=DsNrtayqONfnWc3gQUi4Dw&expires=1749459196",
        "referer": "https://stylisheleg4nt.com",
        "origin": "https://stylisheleg4nt.com"
    },
    {
        "name": "Sky Sports 3",
        "id": "sky3nz",
        "logo": "https://raw.githubusercontent.com/abusaeeidx/Tv-Channel-Logo/heads/main/CricHD/runded/56-by-xfireflix.png",
        "link": "https://off1.gogohaalmal.com:1686/hls/sky3nz.m3u8?md5=WIO7necwoBuYSd-0__gDIQ&expires=1749459196",
        "referer": "https://stylisheleg4nt.com",
        "origin": "https://stylisheleg4nt.com"
    },
    {
        "name": "Sky Sports 4",
        "id": "sky4nz",
        "logo": "https://raw.githubusercontent.com/abusaeeidx/Tv-Channel-Logo/heads/main/CricHD/runded/56-by-xfireflix.png",
        "link": "https://off1.gogohaalmal.com:1686/hls/sky4nz.m3u8?md5=2867m2gAt2Gl8plNfNBC-Q&expires=1749459196",
        "referer": "https://stylisheleg4nt.com",
        "origin": "https://stylisheleg4nt.com"
    },
    {
        "name": "Sky Sports 5",
        "id": "sky5nz",
        "logo": "https://raw.githubusercontent.com/abusaeeidx/Tv-Channel-Logo/heads/main/CricHD/runded/56-by-xfireflix.png",
        "link": "https://off1.gogohaalmal.com:1686/hls/sky5nz.m3u8?md5=Mxpy6oO4c7xg7owEYADhIA&expires=1749459197",
        "referer": "https://stylisheleg4nt.com",
        "origin": "https://stylisheleg4nt.com"
    },
    {
        "name": "Sky Sports 6",
        "id": "sky6nz",
        "logo": "https://raw.githubusercontent.com/abusaeeidx/Tv-Channel-Logo/heads/main/CricHD/runded/56-by-xfireflix.png",
        "link": "https://off1.gogohaalmal.com:1686/hls/sky6nz.m3u8?md5=NfGS295fPIwztc9paHLIpw&expires=1749459197",
        "referer": "https://stylisheleg4nt.com",
        "origin": "https://stylisheleg4nt.com"
    },
    {
        "name": "Sky Sports 7",
        "id": "sky7nz",
        "logo": "https://raw.githubusercontent.com/abusaeeidx/Tv-Channel-Logo/heads/main/CricHD/runded/56-by-xfireflix.png",
        "link": "https://off1.gogohaalmal.com:1686/hls/sky7nz.m3u8?md5=z1g2E8eCzOswXmdxBGs27Q&expires=1749459197",
        "referer": "https://stylisheleg4nt.com",
        "origin": "https://stylisheleg4nt.com"
    },
    {
        "name": "Sky Sports 8",
        "id": "sky8nz",
        "logo": "https://raw.githubusercontent.com/abusaeeidx/Tv-Channel-Logo/heads/main/CricHD/runded/56-by-xfireflix.png",
        "link": "https://off1.gogohaalmal.com:1686/hls/sky8nz.m3u8?md5=XwoQkAJ_HIEX_me4EyBjMQ&expires=1749459197",
        "referer": "https://stylisheleg4nt.com",
        "origin": "https://stylisheleg4nt.com"
    },
    {
        "name": "Sky Sports 9",
        "id": "sky9nz",
        "logo": "https://raw.githubusercontent.com/abusaeeidx/Tv-Channel-Logo/heads/main/CricHD/runded/56-by-xfireflix.png",
        "link": "https://off1.gogohaalmal.com:1686/hls/sky9nz.m3u8?md5=wBWhwgTeygf_Tuj2uEyG-A&expires=1749459197",
        "referer": "https://stylisheleg4nt.com",
        "origin": "https://stylisheleg4nt.com"
    },
    {
        "name": "Sky Cinema",
        "id": "skysme",
        "logo": "https://raw.githubusercontent.com/abusaeeidx/Tv-Channel-Logo/heads/main/CricHD/runded/skycinema.png",
        "link": "https://off1.gogohaalmal.com:1686/hls/skysme.m3u8?md5=jBqKX5Ocr825GDOy51TC4Q&expires=1749459197",
        "referer": "https://stylisheleg4nt.com",
        "origin": "https://stylisheleg4nt.com"
    },
    {
        "name": "Sky Sports Action",
        "id": "skysact",
        "logo": "https://raw.githubusercontent.com/abusaeeidx/Tv-Channel-Logo/heads/main/CricHD/runded/1745007829332.png",
        "link": "https://off1.gogohaalmal.com:1686/hls/skysact.m3u8?md5=GSY32RrjHlPyqRCwoOoAnw&expires=1749459197",
        "referer": "https://stylisheleg4nt.com",
        "origin": "https://stylisheleg4nt.com"
    },
    {
        "name": "Sky Sports Golf",
        "id": "skysgol",
        "logo": "https://raw.githubusercontent.com/abusaeeidx/Tv-Channel-Logo/heads/main/CricHD/runded/1745008055327.png",
        "link": "https://off1.gogohaalmal.com:1686/hls/skysgol.m3u8?md5=cIynZ7HL7VLN0ijSOSHBwA&expires=1749459197",
        "referer": "https://stylisheleg4nt.com",
        "origin": "https://stylisheleg4nt.com"
    },
    {
        "name": "Sky Sports Premier League",
        "id": "skysprem",
        "logo": "https://raw.githubusercontent.com/abusaeeidx/Tv-Channel-Logo/heads/main/CricHD/runded/43-by-xfireflix.png",
        "link": "https://off1.gogohaalmal.com:1686/hls/skysprem.m3u8?md5=ItVuyz_FCbZAW8skLebE_A&expires=1749459197",
        "referer": "https://stylisheleg4nt.com",
        "origin": "https://stylisheleg4nt.com"
    },
    {
        "name": "Sky Sports Football",
        "id": "skysfott",
        "logo": "https://raw.githubusercontent.com/abusaeeidx/Tv-Channel-Logo/heads/main/CricHD/runded/44-by-xfireflix.png",
        "link": "https://off1.gogohaalmal.com:1686/hls/skysfott.m3u8?md5=lOCgK2GgZBG55YyCgOPw9g&expires=1749459197",
        "referer": "https://stylisheleg4nt.com",
        "origin": "https://stylisheleg4nt.com"
    },
    {
        "name": "Sky Sports Plus",
        "id": "skysare",
        "logo": "https://raw.githubusercontent.com/abusaeeidx/Tv-Channel-Logo/heads/main/CricHD/runded/1745008347584.png",
        "link": "https://off1.gogohaalmal.com:1686/hls/skysare.m3u8?md5=znaQilTk6W1S6j9M95qwvQ&expires=1749459198",
        "referer": "https://stylisheleg4nt.com",
        "origin": "https://stylisheleg4nt.com"
    },
    {
        "name": "Sky Sports F1",
        "id": "skysfor1",
        "logo": "https://raw.githubusercontent.com/abusaeeidx/Tv-Channel-Logo/heads/main/CricHD/runded/1745008468637.png",
        "link": "https://off1.gogohaalmal.com:1686/hls/skysfor1.m3u8?md5=qBqpkX17XW-KZjsBi0Y3Cg&expires=1749459198",
        "referer": "https://stylisheleg4nt.com",
        "origin": "https://stylisheleg4nt.com"
    },
    {
        "name": "LaLiGA",
        "id": "laligauk",
        "logo": "https://raw.githubusercontent.com/abusaeeidx/Tv-Channel-Logo/heads/main/CricHD/runded/19-by-xfireflix.png",
        "link": "https://off1.gogohaalmal.com:1686/hls/laligauk.m3u8?md5=vZyaLQU5DJGRHlxV0eVD5A&expires=1749459198",
        "referer": "https://stylisheleg4nt.com",
        "origin": "https://stylisheleg4nt.com"
    },
    {
        "name": "Premier Sports 1",
        "id": "premieruk",
        "logo": "https://raw.githubusercontent.com/abusaeeidx/Tv-Channel-Logo/heads/main/CricHD/runded/31-by-xfireflix.png",
        "link": "https://off1.gogohaalmal.com:1686/hls/premieruk.m3u8?md5=AN5mGIgwMgBdldMghOixPQ&expires=1749459198",
        "referer": "https://stylisheleg4nt.com",
        "origin": "https://stylisheleg4nt.com"
    },
    {
        "name": "Premier Sports 2",
        "id": "hdchnl2",
        "logo": "https://raw.githubusercontent.com/abusaeeidx/Tv-Channel-Logo/heads/main/CricHD/runded/31-by-xfireflix.png",
        "link": "https://off1.gogohaalmal.com:1686/hls/hdchnl2.m3u8?md5=2sDB7TzN2rVCLM3a4hoL7A&expires=1749459198",
        "referer": "https://stylisheleg4nt.com",
        "origin": "https://stylisheleg4nt.com"
    },
    {
        "name": "Super Football",
        "id": "superfotball",
        "logo": "https://raw.githubusercontent.com/abusaeeidx/Tv-Channel-Logo/heads/main/CricHD/runded/34-by-xfireflix.png",
        "link": "https://off1.gogohaalmal.com:1686/hls/superfotball.m3u8?md5=vUPufnhJW_UwRzYyv372Iw&expires=1749459198",
        "referer": "https://stylisheleg4nt.com",
        "origin": "https://stylisheleg4nt.com"
    },
    {
        "name": "Super Premier League",
        "id": "superpremier",
        "logo": "https://raw.githubusercontent.com/abusaeeidx/Tv-Channel-Logo/heads/main/CricHD/runded/1745008781606.png",
        "link": "https://off1.gogohaalmal.com:1686/hls/superpremier.m3u8?md5=HZ8SY55FOK98EjtJN4VMig&expires=1749459198",
        "referer": "https://stylisheleg4nt.com",
        "origin": "https://stylisheleg4nt.com"
    },
    {
        "name": "Astro Cricket",
        "id": "fox501",
        "logo": "https://raw.githubusercontent.com/abusaeeidx/Tv-Channel-Logo/heads/main/CricHD/runded/1745008895589.png",
        "link": "https://off1.gogohaalmal.com:1686/hls/fox501.m3u8?md5=0QfJC2_r4qFF8akfTcGqBw&expires=1749459198",
        "referer": "https://stylisheleg4nt.com",
        "origin": "https://stylisheleg4nt.com"
    },
    {
        "name": "ESPN 1",
        "id": "espnusa",
        "logo": "https://raw.githubusercontent.com/abusaeeidx/Tv-Channel-Logo/heads/main/CricHD/runded/17-by-xfireflix.png",
        "link": "https://off1.gogohaalmal.com:1686/hls/espnusa.m3u8?md5=Kmbz6_UICZRNut-CBuMvuQ&expires=1749459198",
        "referer": "https://stylisheleg4nt.com",
        "origin": "https://stylisheleg4nt.com"
    },
    {
        "name": "ESPN 2",
        "id": "espn2",
        "logo": "https://raw.githubusercontent.com/abusaeeidx/Tv-Channel-Logo/heads/main/CricHD/runded/17-by-xfireflix.png",
        "link": "https://off1.gogohaalmal.com:1686/hls/espn2.m3u8?md5=_GCunHSPtl2PzJiJHS8tyA&expires=1749459198",
        "referer": "https://stylisheleg4nt.com",
        "origin": "https://stylisheleg4nt.com"
    },
    {
        "name": "Sky Sports Arena",
        "id": "skysare",
        "logo": "https://raw.githubusercontent.com/abusaeeidx/Tv-Channel-Logo/heads/main/CricHD/runded/1745007829327.png",
        "link": "https://off1.gogohaalmal.com:1686/hls/skysare.m3u8?md5=znaQilTk6W1S6j9M95qwvQ&expires=1749459198",
        "referer": "https://stylisheleg4nt.com",
        "origin": "https://stylisheleg4nt.com"
    },
    {
        "name": "Sky Sports Mix",
        "id": "skysmixx",
        "logo": "https://raw.githubusercontent.com/abusaeeidx/Tv-Channel-Logo/heads/main/CricHD/runded/13-by-xfireflix.png",
        "link": "https://off1.gogohaalmal.com:1686/hls/skysmixx.m3u8?md5=sjDaoyNLZzqu35NOg_n7pg&expires=1749459199",
        "referer": "https://stylisheleg4nt.com",
        "origin": "https://stylisheleg4nt.com"
    },
    {
        "name": "Sky Sports Tennis",
        "id": "skystennis",
        "logo": "https://raw.githubusercontent.com/abusaeeidx/Tv-Channel-Logo/heads/main/CricHD/runded/1745009085794.png",
        "link": "https://off1.gogohaalmal.com:1686/hls/skystennis.m3u8?md5=YhG6ALGgIA3lekLyNm3Fag&expires=1749459199",
        "referer": "https://stylisheleg4nt.com",
        "origin": "https://stylisheleg4nt.com"
    },
    {
        "name": "Fox Cricket 501 HD",
        "id": "fox501",
        "logo": "https://raw.githubusercontent.com/abusaeeidx/Tv-Channel-Logo/heads/main/CricHD/runded/6-by-xfireflix.png",
        "link": "https://off1.gogohaalmal.com:1686/hls/fox501.m3u8?md5=kIOrcVeCkggurqJsp-OaNw&expires=1749459199",
        "referer": "https://stylisheleg4nt.com",
        "origin": "https://stylisheleg4nt.com"
    },
    {
        "name": "Sony Sports3",
        "id": "ten1hd",
        "logo": "https://raw.githubusercontent.com/abusaeeidx/Tv-Channel-Logo/heads/main/CricHD/runded/1000173192-modified.png",
        "link": "https://off1.gogohaalmal.com:1686/hls/ten1hd.m3u8?md5=2sxYITl-50y0IeTzcUz3IQ&expires=1749459199",
        "referer": "https://stylisheleg4nt.com",
        "origin": "https://stylisheleg4nt.com"
    }
]